<?xml version="1.0" encoding="utf-8"?>
<template>
    <name>caweb-addon</name>
    <author>Danny Guzman</author>
    <email>guzmanjd86@gmail.com</email>
    <description>phpDocumentor Template Addon</description>
    <version>1.0.0</version>
    <transformations>
        <!-- Change Branding Logo -->
        <transformation writer="FileIo" query="copy" source="images/system/caweb-logo.png" artifact="imgs/branding.png" />

        <!-- Override cagov.core.css and colorsheme-<color>.css -->
        <transformation writer="FileIo" query="copy" source="css/cagov-v5.5-santa barbara.css" artifact="css/cagov.core.css" />
        <transformation writer="FileIo" query="copy" source="style.css" artifact="css/colorscheme-santabarbara.css" />

        <!-- Override cagov.core.js -->
        <transformation writer="FileIo" query="copy" source="js/caweb-v5.5.js" artifact="js/cagov.core.js" />

        <!-- Override Fonts -->
        <transformation writer="FileIo" query="copy" source="fonts/" artifact="fonts/" />
        
    </transformations>
</template>